repo2lark-0.0.5.dist-info/METADATA
repo2lark-0.0.5.dist-info/WHEEL
repo2lark-0.0.5.dist-info/entry_points.txt
repo2lark-0.0.5.dist-info/licenses/LICENSE
repo2lark/__init__.py
repo2lark/config.py
repo2lark/middleware.py
repo2lark/models.py
repo2lark/router.py
repo2lark/template.json
repo2lark/utils.py
repo2lark-0.0.5.dist-info/RECORD
